olli/__init__.py
olli/__main__.py
olli/alert.py
olli/api.py
olli/config.py
olli/structures.py
olli/webhook.py
olli-2.0.0.dist-info/LICENSE
olli-2.0.0.dist-info/METADATA
olli-2.0.0.dist-info/WHEEL
olli-2.0.0.dist-info/entry_points.txt
olli-2.0.0.dist-info/RECORD
